semtools/__init__.py
semtools/cli.py
semtools/config.py
semtools/parse/__init__.py
semtools/parse/backend.py
semtools/parse/cache.py
semtools/parse/client.py
semtools/parse/config.py
semtools/parse/enums.py
semtools/parse/errors.py
semtools/search/__init__.py
semtools/search/core.py
semtools/search/enums.py
semtools/search/loader.py
semtools/search/models.py
semtools/search/presenter.py
semtools/workspace/__init__.py
semtools/workspace/core.py
semtools/workspace/errors.py
semtools/workspace/models.py
semtools/workspace/store.py
semtools_py-0.1.0.dist-info/METADATA
semtools_py-0.1.0.dist-info/WHEEL
semtools_py-0.1.0.dist-info/entry_points.txt
semtools_py-0.1.0.dist-info/RECORD
