Metadata-Version: 2.4
Name: semtools-py
Version: 0.1.0
Summary: Semantic search and document parsing tools for the command line
Requires-Python: >=3.13
Requires-Dist: aiofiles
Requires-Dist: click
Requires-Dist: httpx
Requires-Dist: lancedb
Requires-Dist: model2vec
Requires-Dist: numpy
Requires-Dist: scipy
